setup.py
dnspod/__init__.py
dnspod/base.py
dnspod/domain.py
dnspod/info.py
dnspod/record.py
dnspod/version.py
dnspod.egg-info/PKG-INFO
dnspod.egg-info/SOURCES.txt
dnspod.egg-info/dependency_links.txt
dnspod.egg-info/requires.txt
dnspod.egg-info/top_level.txt