Metadata-Version: 1.1
Name: dnspod
Version: 0.1.2
Summary: a Python library for DNSPod OpenAPI
Home-page: https://github.com/leeyiw/dnspod
Author: Yiwei Li
Author-email: leeyiw@gmail.com
License: Apache
Platform: UNKNOWN
Classifier: Development Status :: 3 - Alpha
Classifier: Environment :: Console
Classifier: Intended Audience :: Developers
Classifier: Intended Audience :: System Administrators
Classifier: License :: OSI Approved :: Apache Software License
Classifier: Natural Language :: English
Classifier: Programming Language :: Python
Classifier: Programming Language :: Python :: 2
